spk_logger/__init__.py
spk_logger/base_models.py
spk_logger/logger.py
spk_logger-0.2.1.dist-info/LICENSE
spk_logger-0.2.1.dist-info/WHEEL
spk_logger-0.2.1.dist-info/METADATA
spk_logger-0.2.1.dist-info/RECORD
