Metadata-Version: 2.1
Name: spk-logger
Version: 0.2.1
Summary: Spk-logger is a tool developed to monitor machine learning models put into production through logs.
Home-page: https://github.com/SpikeLab-CL/spk-logger
License: MIT
Author: NicolasITC
Author-email: n.treimun14@gmail.com
Requires-Python: >=3.7,<3.8
Classifier: License :: OSI Approved :: MIT License
Classifier: Programming Language :: Python :: 3
Classifier: Programming Language :: Python :: 3.7
Requires-Dist: google-cloud-logging (>=2.2.0,<2.3.0)
Requires-Dist: pendulum (>=2.1.2,<2.2.0)
Requires-Dist: pickle4 (>=0.0.1,<0.1.0)
Requires-Dist: pydantic (>=1.7.3,<1.8.0)
Project-URL: Repository, https://github.com/SpikeLab-CL/spk-logger
